QUEEN/cutsite.py
QUEEN/qdiff.py
QUEEN/qfunction.py
QUEEN/qgraph.py
QUEEN/qint.py
QUEEN/qobj.py
QUEEN/qprocess.py
QUEEN/qseq.py
QUEEN/queen.py
QUEEN/quine.py
QUEEN/visualize_circular_dna.py
QUEEN/visualize_linear_dna.py
python_queen-1.0.1.dist-info/LICENSE
python_queen-1.0.1.dist-info/METADATA
python_queen-1.0.1.dist-info/WHEEL
python_queen-1.0.1.dist-info/top_level.txt
python_queen-1.0.1.dist-info/RECORD
