Metadata-Version: 2.1
Name: python-queen
Version: 1.0.1
Summary: QUEEN (a Python module to universally program, QUinE, and Edit Nucleotide sequences)
Home-page: https://github.com/yachielab/QUEEN
Author: Hideto Mori
Author-email: hidto7592@gmail.com
Maintainer: Hideto Mori
Maintainer-email: hidto7592@gmail.com
License: MIT
Download-URL: https://github.com/yachielab/QUEEN
Platform: UNKNOWN
Classifier: Intended Audience :: Science/Research
Classifier: Programming Language :: Python :: 3.7
Classifier: Programming Language :: Python :: 3.8
Classifier: Programming Language :: Python :: 3.9
Classifier: License :: OSI Approved :: MIT License
Requires-Python: >=3.7
License-File: LICENSE
Requires-Dist: numpy (>=1.2)
Requires-Dist: biopython (>=1.78)
Requires-Dist: matplotlib (>=3.2)
Requires-Dist: requests (~=2.23.0)
Requires-Dist: regex (>=2.5)
Requires-Dist: graphviz (==0.17)
Requires-Dist: beautifulsoup4 (>=4.4)
